moldoc/__init__.py
moldoc/molecule.py
moldoc/py.typed
moldoc/version.py
moldoc/_internal/__init__.py
moldoc/_internal/molDraw.js
moldoc/_internal/moldoc.py
moldoc/_internal/molecule.py
moldoc/_internal/three.min.js
moldoc/_internal/javascript/__init__.py
moldoc/_internal/javascript/atoms.py
moldoc/_internal/javascript/bonds.py
moldoc/_internal/javascript/bool.py
moldoc/_internal/javascript/color.py
moldoc/_internal/javascript/material.py
moldoc/_internal/javascript/mesh_config.py
moldoc/_internal/javascript/scene_config.py
moldoc-3.0.5.dist-info/LICENSE
moldoc-3.0.5.dist-info/METADATA
moldoc-3.0.5.dist-info/WHEEL
moldoc-3.0.5.dist-info/top_level.txt
moldoc-3.0.5.dist-info/RECORD
