Metadata-Version: 2.1
Name: moldoc
Version: 3.0.5
Summary: Make better chemistry documentation!
Maintainer-email: Lukas Turcani <lukasturcani93@gmail.com>
Project-URL: github, https://github.com/lukasturcani/moldoc
Requires-Python: >=3.10
License-File: LICENSE
Requires-Dist: sphinx
Provides-Extra: dev
Requires-Dist: ruff ; extra == 'dev'
Requires-Dist: mypy ; extra == 'dev'
Requires-Dist: build ; extra == 'dev'
Requires-Dist: twine ; extra == 'dev'
Requires-Dist: types-docutils ; extra == 'dev'
Requires-Dist: furo ; extra == 'dev'
